seagliderOG1/__init__.py
seagliderOG1/_version.py
seagliderOG1/convertOG1.py
seagliderOG1/old-tools.py
seagliderOG1/plotters.py
seagliderOG1/readers.py
seagliderOG1/tools.py
seagliderOG1/utilities.py
seagliderOG1/vocabularies.py
seagliderOG1/writers.py
seagliderOG1/config/OG1_author.yaml
seagliderOG1/config/OG1_global_attrs.yaml
seagliderOG1/config/OG1_sensor_attrs.yaml
seagliderOG1/config/OG1_var_names.yaml
seagliderOG1/config/OG1_vocab_attrs.yaml
seagliderOG1/config/mission_yaml.yaml
seagliderog1-0.0.2.dist-info/licenses/LICENSE
seagliderog1-0.0.2.dist-info/METADATA
seagliderog1-0.0.2.dist-info/WHEEL
seagliderog1-0.0.2.dist-info/top_level.txt
seagliderog1-0.0.2.dist-info/RECORD
