Metadata-Version: 2.4
Name: seagliderOG1
Version: 0.0.2
Summary: Convert from Seaglider basestation to OG1 format
Maintainer-email: Eleanor Frajka-Williams <eleanorfrajka@gmail.com>, Till Moritz <till.moritz@uni-hamburg.de>
License: MIT License
Project-URL: documentation, https://github.com/ocean-uhh/seagliderOG1
Project-URL: homepage, https://github.com/ocean-uhh/seagliderOG1
Project-URL: repository, https://github.com/ocean-uhh/seagliderOG1
Classifier: Programming Language :: Python :: 3 :: Only
Classifier: Programming Language :: Python :: 3.8
Classifier: Programming Language :: Python :: 3.9
Classifier: Programming Language :: Python :: 3.10
Classifier: Programming Language :: Python :: 3.11
Classifier: Programming Language :: Python :: 3.12
Requires-Python: >=3.8
License-File: LICENSE
Requires-Dist: numpy>=1.23
Requires-Dist: scipy>=1.10
Requires-Dist: pandas>=2.1
Requires-Dist: netCDF4>=1.6
Requires-Dist: xarray>=2025.1.1
Requires-Dist: pooch>=1.7
Requires-Dist: beautifulsoup4>=4.12
Requires-Dist: requests>=2.31
Requires-Dist: gsw>=3.6
Requires-Dist: cartopy>=0.21
Requires-Dist: matplotlib>=3.6
Requires-Dist: tqdm>=4.65
Dynamic: license-file
